lolla/__init__.py
lolla/log.py
lolla/lolla.py
lolla/ollama.py
lolla/parser.py
lolla/storage.py
lolla/tools.py
lolla-0.1.2.dist-info/LICENSE
lolla-0.1.2.dist-info/METADATA
lolla-0.1.2.dist-info/WHEEL
lolla-0.1.2.dist-info/entry_points.txt
lolla-0.1.2.dist-info/top_level.txt
lolla-0.1.2.dist-info/RECORD
