Metadata-Version: 2.1
Name: lolla
Version: 0.1.2
Summary: Local Ollama CLI
Home-page: https://github.com/Lunik/lolla
Download-URL: https://pypi.org/project/lolla/
Author: Guillaume MARTINEZ
Author-email: lunik@tiwabbit.fr
Maintainer: Guillaume MARTINEZ
Maintainer-email: lunik@tiwabbit.fr
Classifier: Development Status :: 3 - Alpha
Classifier: Intended Audience :: Developers
Classifier: Intended Audience :: Information Technology
Classifier: Intended Audience :: System Administrators
Classifier: Topic :: Software Development :: Build Tools
Classifier: License :: OSI Approved :: GNU General Public License v3 (GPLv3)
Classifier: Programming Language :: Python :: 3
Classifier: Programming Language :: Python :: 3.10
Classifier: Programming Language :: Python :: 3.11
Requires-Python: >=3.10.0
License-File: LICENSE
Requires-Dist: rich ==13.*
Requires-Dist: requests ==2.*
Provides-Extra: dev
Requires-Dist: pylint ; extra == 'dev'
Requires-Dist: black ; extra == 'dev'
Requires-Dist: twine ; extra == 'dev'
Requires-Dist: build ; extra == 'dev'
Requires-Dist: pyinstaller ; extra == 'dev'
Requires-Dist: wheel ; extra == 'dev'
